telegram_bot_discussion/__init__.py
telegram_bot_discussion/bot/__init__.py
telegram_bot_discussion/bot/bot.py
telegram_bot_discussion/bot/contextual.py
telegram_bot_discussion/bot/exceptions/__init__.py
telegram_bot_discussion/bot/exceptions/buttons_handler_is_not_set.py
telegram_bot_discussion/bot/exceptions/commands_handler_is_not_set.py
telegram_bot_discussion/bot/exceptions/replicas_handler_is_not_set.py
telegram_bot_discussion/button/__init__.py
telegram_bot_discussion/button/button.py
telegram_bot_discussion/button/button_meta.py
telegram_bot_discussion/button/buttons_map.py
telegram_bot_discussion/button/coder_interface.py
telegram_bot_discussion/button/params/__init__.py
telegram_bot_discussion/button/params/params.py
telegram_bot_discussion/command/__init__.py
telegram_bot_discussion/command/command.py
telegram_bot_discussion/command/command_meta.py
telegram_bot_discussion/command/commands_map.py
telegram_bot_discussion/config/__init__.py
telegram_bot_discussion/config/config.py
telegram_bot_discussion/constants/__init__.py
telegram_bot_discussion/constants/constants.py
telegram_bot_discussion/dialogue/__init__.py
telegram_bot_discussion/dialogue/dialogue.py
telegram_bot_discussion/dialogue/replicas/__init__.py
telegram_bot_discussion/dialogue/replicas/base.py
telegram_bot_discussion/ext/__init__.py
telegram_bot_discussion/ext/button/__init__.py
telegram_bot_discussion/ext/button/change_button_at_keyboard.py
telegram_bot_discussion/ext/coder/__init__.py
telegram_bot_discussion/ext/coder/bsv_coder.py
telegram_bot_discussion/ext/coder/store_coder.py
telegram_bot_discussion/ext/command/__init__.py
telegram_bot_discussion/ext/command/commands_menu.py
telegram_bot_discussion/ext/command_button/__init__.py
telegram_bot_discussion/ext/command_button/command_button.py
telegram_bot_discussion/ext/command_button/command_button_param.py
telegram_bot_discussion/ext/command_button/commands_buttons_menu.py
telegram_bot_discussion/ext/logger/__init__.py
telegram_bot_discussion-1.0.0.dist-info/licenses/LICENSE
telegram_bot_discussion-1.0.0.dist-info/METADATA
telegram_bot_discussion-1.0.0.dist-info/WHEEL
telegram_bot_discussion-1.0.0.dist-info/top_level.txt
telegram_bot_discussion-1.0.0.dist-info/RECORD
