Metadata-Version: 2.4
Name: telegram-bot-discussion
Version: 1.0.0
Summary: Telegram-bot framework `telegram-bot-discussion` based on native Telegram Bot API Python-library `python-telegram-bot`.
Author: ILYA
Keywords: Python Telegram-bot Framework
Classifier: Programming Language :: Python :: 3.9
Classifier: Intended Audience :: Developers
Classifier: Topic :: Software Development :: Build Tools
Classifier: Operating System :: OS Independent
Requires-Python: >=3.9
License-File: LICENSE
Requires-Dist: python-telegram-bot>=22.0
Dynamic: author
Dynamic: classifier
Dynamic: description
Dynamic: description-content-type
Dynamic: keywords
Dynamic: license-file
Dynamic: requires-dist
Dynamic: requires-python
Dynamic: summary
